common/__init__.py
common/errors.py
model/__init__.py
model/librml.py
model/names.py
tmpl/TemplateManager.py
tmpl/__init__.py
tmpl/templateutils.py
pylibrml-0.2.0.dev1.dist-info/LICENSE
pylibrml-0.2.0.dev1.dist-info/METADATA
pylibrml-0.2.0.dev1.dist-info/WHEEL
pylibrml-0.2.0.dev1.dist-info/top_level.txt
pylibrml-0.2.0.dev1.dist-info/RECORD
